CHANGELOG.txt
LICENSE.txt
MANIFEST.in
README.txt
setup.py
Rottutils.egg-info/PKG-INFO
Rottutils.egg-info/SOURCES.txt
Rottutils.egg-info/dependency_links.txt
Rottutils.egg-info/top_level.txt
rottutils/__init__.py