Metadata-Version: 2.1
Name: Rottutils
Version: 0.0.1.1
Summary: Py library with useful utilities.
Home-page: https://github.com/Rotthin
Author: Maciej 'Rotthin' Niziołek
Author-email: rotthin_dev@protonmail.com
License: MIT
Platform: UNKNOWN
Classifier: Development Status :: 5 - Production/Stable
Classifier: Operating System :: OS Independent
Classifier: License :: OSI Approved :: MIT License
Classifier: Programming Language :: Python :: 3
License-File: LICENSE.txt
